icd10/__init__.py
icd10/code2description.py
icd10_c2d-0.0.2.dist-info/LICENSE
icd10_c2d-0.0.2.dist-info/METADATA
icd10_c2d-0.0.2.dist-info/WHEEL
icd10_c2d-0.0.2.dist-info/top_level.txt
icd10_c2d-0.0.2.dist-info/RECORD
