Metadata-Version: 2.1
Name: icd10-c2d
Version: 0.0.2
Summary: A package to get ICD10 Description from ICD10 Codes
Home-page: https://github.com/pypa/sampleproject
Author: Kantheti Saket Ram
Author-email: sakethaux1111@gmail.com
License: UNKNOWN
Platform: UNKNOWN
Classifier: Programming Language :: Python :: 3.5
Classifier: License :: OSI Approved :: MIT License
Classifier: Operating System :: OS Independent
Requires-Python: >=3.5
Requires-Dist: requests
Requires-Dist: beautifulsoup4
Requires-Dist: pandas
